{
  "info": {
    "_postman_id": "a1b2c3d4-e5f6-7a8b-9c0d-1e2f3a4b5c6d",
    "name": "MERN Job Portal REST API Collection",
    "description": "Comprehensive REST API requests covering Candidates, Employers, Public Listings, Notifications, and Admin management for the MERN Job Portal System.",
    "schema": "https://schema.getpostman.com/json/collection/v2.1.0/collection.json"
  },
  "item": [
    {
      "name": "1. Authentication",
      "item": [
        {
          "name": "Register Candidate",
          "request": {
            "method": "POST",
            "header": [],
            "body": {
              "mode": "raw",
              "raw": "{\n  \"firstName\": \"Alex\",\n  \"lastName\": \"Smith\",\n  \"email\": \"alex.smith@example.com\",\n  \"password\": \"Password@123\",\n  \"role\": \"candidate\"\n}",
              "options": {
                "raw": {
                  "language": "json"
                }
              }
            },
            "url": {
              "raw": "{{baseUrl}}/auth/register",
              "host": [
                "{{baseUrl}}"
              ],
              "path": [
                "auth",
                "register"
              ]
            }
          },
          "response": []
        },
        {
          "name": "Register Employer",
          "request": {
            "method": "POST",
            "header": [],
            "body": {
              "mode": "raw",
              "raw": "{\n  \"firstName\": \"Sarah\",\n  \"lastName\": \"Jones\",\n  \"email\": \"sarah.jones@example.com\",\n  \"password\": \"Password@123\",\n  \"role\": \"employer\"\n}",
              "options": {
                "raw": {
                  "language": "json"
                }
              }
            },
            "url": {
              "raw": "{{baseUrl}}/auth/register",
              "host": [
                "{{baseUrl}}"
              ],
              "path": [
                "auth",
                "register"
              ]
            }
          },
          "response": []
        },
        {
          "name": "Login User",
          "event": [
            {
              "listen": "test",
              "script": {
                "exec": [
                  "var jsonData = pm.response.json();",
                  "if (jsonData.success && jsonData.data && jsonData.data.accessToken) {",
                  "    pm.environment.set(\"accessToken\", jsonData.data.accessToken);",
                  "}"
                ],
                "type": "text/javascript"
              }
            }
          ],
          "request": {
            "method": "POST",
            "header": [],
            "body": {
              "mode": "raw",
              "raw": "{\n  \"email\": \"alex.smith@example.com\",\n  \"password\": \"Password@123\"\n}",
              "options": {
                "raw": {
                  "language": "json"
                }
              }
            },
            "url": {
              "raw": "{{baseUrl}}/auth/login",
              "host": [
                "{{baseUrl}}"
              ],
              "path": [
                "auth",
                "login"
              ]
            }
          },
          "response": []
        },
        {
          "name": "Get Current User",
          "request": {
            "method": "GET",
            "header": [
              {
                "key": "Authorization",
                "value": "Bearer {{accessToken}}",
                "type": "text"
              }
            ],
            "url": {
              "raw": "{{baseUrl}}/auth/me",
              "host": [
                "{{baseUrl}}"
              ],
              "path": [
                "auth",
                "me"
              ]
            }
          },
          "response": []
        },
        {
          "name": "Change Password",
          "request": {
            "method": "PATCH",
            "header": [
              {
                "key": "Authorization",
                "value": "Bearer {{accessToken}}",
                "type": "text"
              }
            ],
            "body": {
              "mode": "raw",
              "raw": "{\n  \"currentPassword\": \"Password@123\",\n  \"newPassword\": \"NewPassword@123\"\n}",
              "options": {
                "raw": {
                  "language": "json"
                }
              }
            },
            "url": {
              "raw": "{{baseUrl}}/auth/change-password",
              "host": [
                "{{baseUrl}}"
              ],
              "path": [
                "auth",
                "change-password"
              ]
            }
          },
          "response": []
        },
        {
          "name": "Refresh Access Token",
          "request": {
            "method": "POST",
            "header": [],
            "url": {
              "raw": "{{baseUrl}}/auth/refresh-token",
              "host": [
                "{{baseUrl}}"
              ],
              "path": [
                "auth",
                "refresh-token"
              ]
            }
          },
          "response": []
        },
        {
          "name": "Logout User",
          "request": {
            "method": "POST",
            "header": [],
            "url": {
              "raw": "{{baseUrl}}/auth/logout",
              "host": [
                "{{baseUrl}}"
              ],
              "path": [
                "auth",
                "logout"
              ]
            }
          },
          "response": []
        }
      ]
    },
    {
      "name": "2. Candidate Features",
      "item": [
        {
          "name": "Get Profile",
          "request": {
            "method": "GET",
            "header": [
              {
                "key": "Authorization",
                "value": "Bearer {{accessToken}}",
                "type": "text"
              }
            ],
            "url": {
              "raw": "{{baseUrl}}/candidates/profile",
              "host": [
                "{{baseUrl}}"
              ],
              "path": [
                "candidates",
                "profile"
              ]
            }
          },
          "response": []
        },
        {
          "name": "Update Profile",
          "request": {
            "method": "PUT",
            "header": [
              {
                "key": "Authorization",
                "value": "Bearer {{accessToken}}",
                "type": "text"
              }
            ],
            "body": {
              "mode": "raw",
              "raw": "{\n  \"phone\": \"+919988776655\",\n  \"headline\": \"Software Engineer | MERN Developer\",\n  \"summary\": \"Aspiring developer with experience in Node, React, and MongoDB.\",\n  \"customSkills\": [\"React\", \"NodeJS\", \"TailwindCSS\"],\n  \"languages\": [\n    {\n      \"language\": \"English\",\n      \"proficiency\": \"fluent\"\n    }\n  ]\n}",
              "options": {
                "raw": {
                  "language": "json"
                }
              }
            },
            "url": {
              "raw": "{{baseUrl}}/candidates/profile",
              "host": [
                "{{baseUrl}}"
              ],
              "path": [
                "candidates",
                "profile"
              ]
            }
          },
          "response": []
        },
        {
          "name": "Get Dashboard Details",
          "request": {
            "method": "GET",
            "header": [
              {
                "key": "Authorization",
                "value": "Bearer {{accessToken}}",
                "type": "text"
              }
            ],
            "url": {
              "raw": "{{baseUrl}}/candidates/dashboard",
              "host": [
                "{{baseUrl}}"
              ],
              "path": [
                "candidates",
                "dashboard"
              ]
            }
          },
          "response": []
        },
        {
          "name": "Get Job Recommendations",
          "request": {
            "method": "GET",
            "header": [
              {
                "key": "Authorization",
                "value": "Bearer {{accessToken}}",
                "type": "text"
              }
            ],
            "url": {
              "raw": "{{baseUrl}}/candidates/recommendations",
              "host": [
                "{{baseUrl}}"
              ],
              "path": [
                "candidates",
                "recommendations"
              ]
            }
          },
          "response": []
        }
      ]
    },
    {
      "name": "3. Employer Features",
      "item": [
        {
          "name": "Get Employer Profile",
          "request": {
            "method": "GET",
            "header": [
              {
                "key": "Authorization",
                "value": "Bearer {{accessToken}}",
                "type": "text"
              }
            ],
            "url": {
              "raw": "{{baseUrl}}/employers/profile",
              "host": [
                "{{baseUrl}}"
              ],
              "path": [
                "employers",
                "profile"
              ]
            }
          },
          "response": []
        },
        {
          "name": "Create Company Profile",
          "request": {
            "method": "POST",
            "header": [
              {
                "key": "Authorization",
                "value": "Bearer {{accessToken}}",
                "type": "text"
              }
            ],
            "body": {
              "mode": "raw",
              "raw": "{\n  \"name\": \"Global Tech\",\n  \"website\": \"https://globaltech.example.com\",\n  \"email\": \"hr@globaltech.example.com\",\n  \"phone\": \"0801234567\",\n  \"industry\": \"Software Engineering\",\n  \"description\": \"Global software outsourcing and platform builds.\",\n  \"headquarters\": \"London, UK\",\n  \"locations\": [\"London\", \"Remote\"],\n  \"size\": \"51-200\"\n}",
              "options": {
                "raw": {
                  "language": "json"
                }
              }
            },
            "url": {
              "raw": "{{baseUrl}}/employers/company",
              "host": [
                "{{baseUrl}}"
              ],
              "path": [
                "employers",
                "company"
              ]
            }
          },
          "response": []
        },
        {
          "name": "Get Company Details",
          "request": {
            "method": "GET",
            "header": [
              {
                "key": "Authorization",
                "value": "Bearer {{accessToken}}",
                "type": "text"
              }
            ],
            "url": {
              "raw": "{{baseUrl}}/employers/company",
              "host": [
                "{{baseUrl}}"
              ],
              "path": [
                "employers",
                "company"
              ]
            }
          },
          "response": []
        },
        {
          "name": "Get Dashboard Analytics",
          "request": {
            "method": "GET",
            "header": [
              {
                "key": "Authorization",
                "value": "Bearer {{accessToken}}",
                "type": "text"
              }
            ],
            "url": {
              "raw": "{{baseUrl}}/employers/dashboard",
              "host": [
                "{{baseUrl}}"
              ],
              "path": [
                "employers",
                "dashboard"
              ]
            }
          },
          "response": []
        }
      ]
    },
    {
      "name": "4. Job Postings",
      "item": [
        {
          "name": "Create Job",
          "request": {
            "method": "POST",
            "header": [
              {
                "key": "Authorization",
                "value": "Bearer {{accessToken}}",
                "type": "text"
              }
            ],
            "body": {
              "mode": "raw",
              "raw": "{\n  \"title\": \"Backend Node.js Developer\",\n  \"description\": \"Looking for a senior Node.js backend developer.\",\n  \"requirements\": [\"3+ years experience with Express\", \"Expertise in MongoDB\"],\n  \"skills\": [\"66a1a111a111a111a111a111\"],\n  \"location\": \"London, UK\",\n  \"locationType\": \"hybrid\",\n  \"salary\": {\n    \"min\": 45000,\n    \"max\": 60000,\n    \"currency\": \"GBP\"\n  },\n  \"experienceLevel\": \"mid\",\n  \"experienceRequired\": { \"min\": 3 },\n  \"educationRequired\": \"Bachelor's degree\",\n  \"jobType\": \"full-time\",\n  \"category\": \"66a2a222a222a222a222a222\"\n}",
              "options": {
                "raw": {
                  "language": "json"
                }
              }
            },
            "url": {
              "raw": "{{baseUrl}}/jobs",
              "host": [
                "{{baseUrl}}"
              ],
              "path": [
                "jobs"
              ]
            }
          },
          "response": []
        },
        {
          "name": "Update Job Details",
          "request": {
            "method": "PUT",
            "header": [
              {
                "key": "Authorization",
                "value": "Bearer {{accessToken}}",
                "type": "text"
              }
            ],
            "body": {
              "mode": "raw",
              "raw": "{\n  \"openings\": 2,\n  \"locationType\": \"remote\"\n}",
              "options": {
                "raw": {
                  "language": "json"
                }
              }
            },
            "url": {
              "raw": "{{baseUrl}}/jobs/:id",
              "host": [
                "{{baseUrl}}"
              ],
              "path": [
                "jobs",
                ":id"
              ]
            }
          },
          "response": []
        },
        {
          "name": "Change Job Status",
          "request": {
            "method": "PATCH",
            "header": [
              {
                "key": "Authorization",
                "value": "Bearer {{accessToken}}",
                "type": "text"
              }
            ],
            "body": {
              "mode": "raw",
              "raw": "{\n  \"status\": \"closed\"\n}",
              "options": {
                "raw": {
                  "language": "json"
                }
              }
            },
            "url": {
              "raw": "{{baseUrl}}/jobs/:id/status",
              "host": [
                "{{baseUrl}}"
              ],
              "path": [
                "jobs",
                ":id",
                "status"
              ]
            }
          },
          "response": []
        },
        {
          "name": "Get Employer Posted Jobs",
          "request": {
            "method": "GET",
            "header": [
              {
                "key": "Authorization",
                "value": "Bearer {{accessToken}}",
                "type": "text"
              }
            ],
            "url": {
              "raw": "{{baseUrl}}/jobs/my-jobs/all",
              "host": [
                "{{baseUrl}}"
              ],
              "path": [
                "jobs",
                "my-jobs",
                "all"
              ]
            }
          },
          "response": []
        }
      ]
    },
    {
      "name": "5. Applications",
      "item": [
        {
          "name": "Apply for Job",
          "request": {
            "method": "POST",
            "header": [
              {
                "key": "Authorization",
                "value": "Bearer {{accessToken}}",
                "type": "text"
              }
            ],
            "body": {
              "mode": "raw",
              "raw": "{\n  \"jobId\": \"66a3a333a333a333a333a333\",\n  \"coverLetter\": \"Excited to apply for this backend developer position.\",\n  \"resumeUrl\": \"https://example.com/resumes/my_cv.pdf\"\n}",
              "options": {
                "raw": {
                  "language": "json"
                }
              }
            },
            "url": {
              "raw": "{{baseUrl}}/applications",
              "host": [
                "{{baseUrl}}"
              ],
              "path": [
                "applications"
              ]
            }
          },
          "response": []
        },
        {
          "name": "Get Candidate Applications",
          "request": {
            "method": "GET",
            "header": [
              {
                "key": "Authorization",
                "value": "Bearer {{accessToken}}",
                "type": "text"
              }
            ],
            "url": {
              "raw": "{{baseUrl}}/applications/my-applications",
              "host": [
                "{{baseUrl}}"
              ],
              "path": [
                "applications",
                "my-applications"
              ]
            }
          },
          "response": []
        },
        {
          "name": "Get Job Applicants",
          "request": {
            "method": "GET",
            "header": [
              {
                "key": "Authorization",
                "value": "Bearer {{accessToken}}",
                "type": "text"
              }
            ],
            "url": {
              "raw": "{{baseUrl}}/applications/job/:jobId",
              "host": [
                "{{baseUrl}}"
              ],
              "path": [
                "applications",
                "job",
                ":jobId"
              ]
            }
          },
          "response": []
        },
        {
          "name": "Schedule Interview",
          "request": {
            "method": "POST",
            "header": [
              {
                "key": "Authorization",
                "value": "Bearer {{accessToken}}",
                "type": "text"
              }
            ],
            "body": {
              "mode": "raw",
              "raw": "{\n  \"scheduledDate\": \"2026-06-25T14:00:00.000Z\",\n  \"scheduledTime\": \"02:30 PM\",\n  \"type\": \"video\",\n  \"meetingLink\": \"https://zoom.us/j/9876543210\",\n  \"notes\": \"Technical discussion covering Javascript async queues and MongoDB indices.\"\n}",
              "options": {
                "raw": {
                  "language": "json"
                }
              }
            },
            "url": {
              "raw": "{{baseUrl}}/applications/:id/interview",
              "host": [
                "{{baseUrl}}"
              ],
              "path": [
                "applications",
                ":id",
                "interview"
              ]
            }
          },
          "response": []
        },
        {
          "name": "Update Status",
          "request": {
            "method": "PATCH",
            "header": [
              {
                "key": "Authorization",
                "value": "Bearer {{accessToken}}",
                "type": "text"
              }
            ],
            "body": {
              "mode": "raw",
              "raw": "{\n  \"status\": \"shortlisted\",\n  \"note\": \"Solid resume matching with required experience.\"\n}",
              "options": {
                "raw": {
                  "language": "json"
                }
              }
            },
            "url": {
              "raw": "{{baseUrl}}/applications/:id/status",
              "host": [
                "{{baseUrl}}"
              ],
              "path": [
                "applications",
                ":id",
                "status"
              ]
            }
          },
          "response": []
        },
        {
          "name": "Withdraw Application",
          "request": {
            "method": "PATCH",
            "header": [
              {
                "key": "Authorization",
                "value": "Bearer {{accessToken}}",
                "type": "text"
              }
            ],
            "url": {
              "raw": "{{baseUrl}}/applications/:id/withdraw",
              "host": [
                "{{baseUrl}}"
              ],
              "path": [
                "applications",
                ":id",
                "withdraw"
              ]
            }
          },
          "response": []
        }
      ]
    },
    {
      "name": "6. Notifications",
      "item": [
        {
          "name": "Get Notifications",
          "request": {
            "method": "GET",
            "header": [
              {
                "key": "Authorization",
                "value": "Bearer {{accessToken}}",
                "type": "text"
              }
            ],
            "url": {
              "raw": "{{baseUrl}}/notifications",
              "host": [
                "{{baseUrl}}"
              ],
              "path": [
                "notifications"
              ]
            }
          },
          "response": []
        },
        {
          "name": "Get Unread Count",
          "request": {
            "method": "GET",
            "header": [
              {
                "key": "Authorization",
                "value": "Bearer {{accessToken}}",
                "type": "text"
              }
            ],
            "url": {
              "raw": "{{baseUrl}}/notifications/unread-count",
              "host": [
                "{{baseUrl}}"
              ],
              "path": [
                "notifications",
                "unread-count"
              ]
            }
          },
          "response": []
        },
        {
          "name": "Mark All Read",
          "request": {
            "method": "PATCH",
            "header": [
              {
                "key": "Authorization",
                "value": "Bearer {{accessToken}}",
                "type": "text"
              }
            ],
            "url": {
              "raw": "{{baseUrl}}/notifications/read-all",
              "host": [
                "{{baseUrl}}"
              ],
              "path": [
                "notifications",
                "read-all"
              ]
            }
          },
          "response": []
        },
        {
          "name": "Mark Read",
          "request": {
            "method": "PATCH",
            "header": [
              {
                "key": "Authorization",
                "value": "Bearer {{accessToken}}",
                "type": "text"
              }
            ],
            "url": {
              "raw": "{{baseUrl}}/notifications/:id/read",
              "host": [
                "{{baseUrl}}"
              ],
              "path": [
                "notifications",
                ":id",
                "read"
              ]
            }
          },
          "response": []
        }
      ]
    },
    {
      "name": "7. Admin moderation",
      "item": [
        {
          "name": "Get Dashboard Stats",
          "request": {
            "method": "GET",
            "header": [
              {
                "key": "Authorization",
                "value": "Bearer {{accessToken}}",
                "type": "text"
              }
            ],
            "url": {
              "raw": "{{baseUrl}}/admin/dashboard/stats",
              "host": [
                "{{baseUrl}}"
              ],
              "path": [
                "admin",
                "dashboard",
                "stats"
              ]
            }
          },
          "response": []
        },
        {
          "name": "List Platform Users",
          "request": {
            "method": "GET",
            "header": [
              {
                "key": "Authorization",
                "value": "Bearer {{accessToken}}",
                "type": "text"
              }
            ],
            "url": {
              "raw": "{{baseUrl}}/admin/users",
              "host": [
                "{{baseUrl}}"
              ],
              "path": [
                "admin",
                "users"
              ]
            }
          },
          "response": []
        },
        {
          "name": "Block/Unblock User",
          "request": {
            "method": "PATCH",
            "header": [
              {
                "key": "Authorization",
                "value": "Bearer {{accessToken}}",
                "type": "text"
              }
            ],
            "body": {
              "mode": "raw",
              "raw": "{\n  \"isBlocked\": true\n}",
              "options": {
                "raw": {
                  "language": "json"
                }
              }
            },
            "url": {
              "raw": "{{baseUrl}}/admin/users/:id/block",
              "host": [
                "{{baseUrl}}"
              ],
              "path": [
                "admin",
                "users",
                ":id",
                "block"
              ]
            }
          },
          "response": []
        },
        {
          "name": "List Pending Employers",
          "request": {
            "method": "GET",
            "header": [
              {
                "key": "Authorization",
                "value": "Bearer {{accessToken}}",
                "type": "text"
              }
            ],
            "url": {
              "raw": "{{baseUrl}}/admin/employers/pending",
              "host": [
                "{{baseUrl}}"
              ],
              "path": [
                "admin",
                "employers",
                "pending"
              ]
            }
          },
          "response": []
        },
        {
          "name": "Approve Employer",
          "request": {
            "method": "PATCH",
            "header": [
              {
                "key": "Authorization",
                "value": "Bearer {{accessToken}}",
                "type": "text"
              }
            ],
            "url": {
              "raw": "{{baseUrl}}/admin/employers/:id/approve",
              "host": [
                "{{baseUrl}}"
              ],
              "path": [
                "admin",
                "employers",
                ":id",
                "approve"
              ]
            }
          },
          "response": []
        },
        {
          "name": "Reject Employer",
          "request": {
            "method": "PATCH",
            "header": [
              {
                "key": "Authorization",
                "value": "Bearer {{accessToken}}",
                "type": "text"
              }
            ],
            "body": {
              "mode": "raw",
              "raw": "{\n  \"rejectionReason\": \"Rejection description indicating failure to produce company license documents.\"\n}",
              "options": {
                "raw": {
                  "language": "json"
                }
              }
            },
            "url": {
              "raw": "{{baseUrl}}/admin/employers/:id/reject",
              "host": [
                "{{baseUrl}}"
              ],
              "path": [
                "admin",
                "employers",
                ":id",
                "reject"
              ]
            }
          },
          "response": []
        },
        {
          "name": "Create Category",
          "request": {
            "method": "POST",
            "header": [
              {
                "key": "Authorization",
                "value": "Bearer {{accessToken}}",
                "type": "text"
              }
            ],
            "body": {
              "mode": "raw",
              "raw": "{\n  \"name\": \"Mobile Apps\",\n  \"icon\": \"FaMobile\",\n  \"description\": \"Swift, Kotlin, React Native development categories.\"\n}",
              "options": {
                "raw": {
                  "language": "json"
                }
              }
            },
            "url": {
              "raw": "{{baseUrl}}/admin/categories",
              "host": [
                "{{baseUrl}}"
              ],
              "path": [
                "admin",
                "categories"
              ]
            }
          },
          "response": []
        },
        {
          "name": "Create Skill",
          "request": {
            "method": "POST",
            "header": [
              {
                "key": "Authorization",
                "value": "Bearer {{accessToken}}",
                "type": "text"
              }
            ],
            "body": {
              "mode": "raw",
              "raw": "{\n  \"name\": \"React Native\",\n  \"category\": \"66a2a222a222a222a222a222\"\n}",
              "options": {
                "raw": {
                  "language": "json"
                }
              }
            },
            "url": {
              "raw": "{{baseUrl}}/admin/skills",
              "host": [
                "{{baseUrl}}"
              ],
              "path": [
                "admin",
                "skills"
              ]
            }
          },
          "response": []
        }
      ]
    },
    {
      "name": "8. Public Endpoints",
      "item": [
        {
          "name": "Get Categories",
          "request": {
            "method": "GET",
            "header": [],
            "url": {
              "raw": "{{baseUrl}}/public/categories",
              "host": [
                "{{baseUrl}}"
              ],
              "path": [
                "public",
                "categories"
              ]
            }
          },
          "response": []
        },
        {
          "name": "Get Skills",
          "request": {
            "method": "GET",
            "header": [],
            "url": {
              "raw": "{{baseUrl}}/public/skills",
              "host": [
                "{{baseUrl}}"
              ],
              "path": [
                "public",
                "skills"
              ]
            }
          },
          "response": []
        },
        {
          "name": "Get Companies List",
          "request": {
            "method": "GET",
            "header": [],
            "url": {
              "raw": "{{baseUrl}}/public/companies",
              "host": [
                "{{baseUrl}}"
              ],
              "path": [
                "public",
                "companies"
              ]
            }
          },
          "response": []
        },
        {
          "name": "Get Company Detail",
          "request": {
            "method": "GET",
            "header": [],
            "url": {
              "raw": "{{baseUrl}}/public/companies/:identifier",
              "host": [
                "{{baseUrl}}"
              ],
              "path": [
                "public",
                "companies",
                ":identifier"
              ]
            }
          },
          "response": []
        },
        {
          "name": "Get Platform Stats",
          "request": {
            "method": "GET",
            "header": [],
            "url": {
              "raw": "{{baseUrl}}/public/stats",
              "host": [
                "{{baseUrl}}"
              ],
              "path": [
                "public",
                "stats"
              ]
            }
          },
          "response": []
        }
      ]
    }
  ]
}
